README.md
setup.cfg
setup.py
sound_downloader/__init__.py
sound_downloader/arguments_parser.py
sound_downloader/conf_manager.py
sound_downloader/downloader.py
sound_downloader/scripts/__init__.py
sound_downloader/scripts/sound_down.py
tests/__init__.py
tests/test_arguments_parser.py
tests/test_conf_manager.py
tests/test_downloader.py
youtube_audio_downloader.egg-info/PKG-INFO
youtube_audio_downloader.egg-info/SOURCES.txt
youtube_audio_downloader.egg-info/dependency_links.txt
youtube_audio_downloader.egg-info/entry_points.txt
youtube_audio_downloader.egg-info/requires.txt
youtube_audio_downloader.egg-info/top_level.txt