Metadata-Version: 1.1
Name: youtube-audio-downloader
Version: 1.1.9
Summary: Download audio from YouTube
Home-page: https://github.com/marcosschroh/youtube-audio-downloader
Author: marcosschroh
Author-email: schrohm@gmail.com
License: GPLv3
Download-URL: https://github.com/marcosschroh/youtube-audio-downloader.git
Keywords: youtube-downloader,downloader,YouTube,youtube,download,audio
Platform: UNKNOWN
